sms_reg_api/__init__.py
sms_reg_api/exceptions.py
sms_reg_api/sms_reg.py
tests/__init__.py
tests/sms_reg_api_tests.py
sms_reg-0.5.dist-info/LICENSE.txt
sms_reg-0.5.dist-info/METADATA
sms_reg-0.5.dist-info/WHEEL
sms_reg-0.5.dist-info/top_level.txt
sms_reg-0.5.dist-info/RECORD
