Metadata-Version: 2.1
Name: sms-reg
Version: 0.5
Summary: Python API for sms-reg.com
Home-page: http://linkedin.com/in/vbxx3
Author: Valentine Bobrovsky
Author-email: vbabrouski@outlook.com
License: MIT
Platform: UNKNOWN
Classifier: Programming Language :: Python :: 3
Classifier: License :: OSI Approved :: MIT License
Classifier: Operating System :: OS Independent
Requires-Dist: setuptools
Requires-Dist: requests
